<?xml version="1.0" encoding="UTF-8"?>
<persistence version="2.1"
	xmlns="http://xmlns.jcp.org/xml/ns/persistence"
	xmlns:xsi="http://www.w3.org/2001/XMLSchema-instance"
	xsi:schemaLocation="http://xmlns.jcp.org/xml/ns/persistence http://xmlns.jcp.org/xml/ns/persistence/persistence_2_1.xsd">
	<persistence-unit name="miUP">
		<provider>org.hibernate.ejb.HibernatePersistence</provider>
		<class>bd.CanalDeVenta</class>
		<class>bd.FamiliaProductora</class>
		<class>bd.Insumo</class>
		<class>bd.ItemDeMateriaPrima</class>
		<class>bd.Lote</class>
		<class>bd.MateriaPrima</class>
		<class>bd.Permiso</class>
		<class>bd.Receta</class>
		<class>bd.StockProductoTerminado</class>
		<class>bd.Usuario</class>
		<properties>
			<property name="javax.persistence.jdbc.driver" value="com.mysql.cj.jdbc.Driver"/>
			<property name="javax.persistence.jdbc.url" value="jdbc:mysql://java-db:3306/jyaa2024_grupo9"/>
			<property name="javax.persistence.jdbc.user" value="jyaa2024_usr9"/>
			<property name="javax.persistence.jdbc.password" value="jyaa2024_pwd9"/>

			<property name="javax.persistence.schema-generation.database.action" value="create"/>
		
			<property name="hibernate.cache.use_second_level_cache" value="false"/>
   			<property name="hibernate.cache.use_query_cache" value="false"/>

			 <property name="hibernate.dialect" value="org.hibernate.dialect.MySQL5InnoDBDialect"/> 
		</properties>
	</persistence-unit>
</persistence>